uaf_compiler/__init__.py
uaf_compiler/builder.py
uaf_compiler/inspector.py
uaf_compiler/loader.py
uaf_compiler/main.py
uaf_compiler/schema.py
uaf_compiler/validator.py
uaf_compiler-0.1.1.dist-info/licenses/LICENSE
uaf_compiler-0.1.1.dist-info/METADATA
uaf_compiler-0.1.1.dist-info/WHEEL
uaf_compiler-0.1.1.dist-info/entry_points.txt
uaf_compiler-0.1.1.dist-info/top_level.txt
uaf_compiler-0.1.1.dist-info/RECORD
