Metadata-Version: 2.4
Name: uaf_compiler
Version: 0.1.1
Summary: Universal Agent File (UAF) Compiler & Protocol
Home-page: https://github.com/DefaultLoop/uaf-compiler
Author: Vaibhav Haswani
Author-email: vaibhav@defaultloop.com
Classifier: Programming Language :: Python :: 3
Classifier: License :: OSI Approved :: Apache Software License
Classifier: Operating System :: OS Independent
Requires-Python: >=3.9
License-File: LICENSE
Requires-Dist: pyyaml
Requires-Dist: pydantic
Dynamic: author
Dynamic: author-email
Dynamic: classifier
Dynamic: description
Dynamic: description-content-type
Dynamic: home-page
Dynamic: license-file
Dynamic: requires-dist
Dynamic: requires-python
Dynamic: summary
